{
    "2026-07-13": {
        "day": "Monday",
        "meals": {
            "Breakfast": [
                "ALOO POHA TIKKI",
                "VEG-UPMA,",
                "CORNFLAKES",
                "BBJ (BUTTER/JAM)",
                "SEASONAL FRUIT",
                "BOILED EGG",
                "TEA/COFFEE/MILK"
            ],
            "Lunch": [
                "MIX -SPROUTS CURRY",
                "ALOO METHI DRY",
                "DAL FRY",
                "RICE",
                "PHULKA",
                "SALAD",
                "PICKLE",
                "N\\A",
                "DAHI",
                "N\\A"
            ],
            "Snacks": [
                "BHEL"
            ],
            "Dinner": [
                "N\\A",
                "VEG KOFTA CURRY",
                "DUDHI CHANA",
                "DAL PLAIN",
                "RICE",
                "PHULKA",
                "N\\A",
                "SALAD",
                "PICKLE",
                "N\\A",
                "LEMON CORINDER"
            ]
        }
    },
    "2026-07-14": {
        "day": "Tuesday",
        "meals": {
            "Breakfast": [
                "MISAL PAV",
                "POHA",
                "CORNFLAKES",
                "BBJ (BUTTER/JAM)",
                "SEASONAL FRUIT",
                "OMLET",
                "TEA/COFFEE/MILK"
            ],
            "Lunch": [
                "KADHI PAKODA",
                "MIX-VEG DRY",
                "MOONG DAL FRY",
                "RICE",
                "PHULKA",
                "SALAD",
                "PICKLE",
                "ROASTED PAPAD",
                "LIMBU PANI",
                "N\\A"
            ],
            "Snacks": [
                "CHANA CHAAT"
            ],
            "Dinner": [
                "METHI MATTER MALAI GRA",
                "SOYA MASALA",
                "DAL",
                "JEERA RICE",
                "PHULKA",
                "N\\A",
                "SALAD",
                "PICKLE",
                "N\\A"
            ]
        }
    },
    "2026-07-15": {
        "day": "Wednesday",
        "meals": {
            "Breakfast": [
                "IDLI , MEDU VADA",
                "SAMBAR, CHUTNEY",
                "CORNFLAKES",
                "BBJ (BUTTER/JAM)",
                "SEASONAL FRUIT",
                "FRENCH TOAST",
                "TEA/COFFEE/MILK"
            ],
            "Lunch": [
                "CHOLE MASALA",
                "VEG BIRYANI",
                "DAL",
                "PHULKA",
                "PICKLE",
                "FRYMUS",
                "RAITA",
                "N\\A"
            ],
            "Snacks": [
                "IDLI MASALA"
            ],
            "Dinner": [
                "CHICKEN CURRY",
                "KVAYDHAI PANEER",
                "DAL",
                "RICE",
                "PHULKA",
                "N\\A",
                "SALAD",
                "PICKLE",
                "TOMATO SOUP"
            ]
        }
    },
    "2026-07-16": {
        "day": "Thursday",
        "meals": {
            "Breakfast": [
                "SEVAI UPMA",
                "BREAD PAKORA",
                "CORNFLAKES",
                "BBJ (BUTTER/JAM)",
                "SEASONAL FRUIT",
                "BOILED EGG",
                "TEA/COFFEE/MILK"
            ],
            "Lunch": [
                "KALA CHANA GRAVY",
                "ALOO CHAWLI DRY",
                "PLAIN DAL",
                "RICE",
                "PHULKA",
                "SALAD",
                "PICKLE",
                "BUTTER MILK",
                "N\\A"
            ],
            "Snacks": [
                "CREAM ROLL"
            ],
            "Dinner": [
                "PAV BHAJI",
                "VEG PULAO",
                "DAL",
                "ROTI",
                "RAITA",
                "PICKLE",
                "DALIYA LAPSHI"
            ]
        }
    },
    "2026-07-17": {
        "day": "Friday",
        "meals": {
            "Breakfast": [
                "UTTAPAM SAMBAR",
                "UPMA",
                "CORNFLAKES",
                "BBJ (BUTTER/JAM)",
                "SEASONAL FRUIT",
                "BOILED EGG",
                "TEA/COFFEE/MILK"
            ],
            "Lunch": [
                "MATTAR USAL",
                "ALOO CORN CAPSICUM",
                "DAL MAKHANI",
                "RICE",
                "PHULKA",
                "PICKLE",
                "VEG- RAITA",
                "N\\A"
            ],
            "Snacks": [
                "MASKA PAV"
            ],
            "Dinner": [
                "EGG BIRYANI",
                "PANEER VEG BIRIYANI",
                "ALOO PYAZA SABJI",
                "DAL",
                "RICE",
                "PHULKA",
                "N\\A",
                "SALAD",
                "PICKLE",
                "N\\A",
                "MANCHOW SOUP"
            ]
        }
    },
    "2026-07-18": {
        "day": "Saturday",
        "meals": {
            "Breakfast": [
                "SABUDANA KHICHADI, DAHI",
                "DHOKLA, CHUTNEY",
                "CORNFLAKES",
                "BBJ (BUTTER/JAM)",
                "SEASONAL FRUIT",
                "FRENCH TOAST",
                "TEA/COFFEE/MILK"
            ],
            "Lunch": [
                "RAJMA MASALA",
                "BEETROOT PORIYAL",
                "DAL TADKA",
                "JEERA RICE",
                "PHULKA",
                "SALAD",
                "PICKLE",
                "KOKAM",
                "N\\A"
            ],
            "Snacks": [
                "KANDA BHAJI"
            ],
            "Dinner": [
                "N\\A",
                "CHOLE MASALA",
                "KADHI",
                "DAL KHICHADI",
                "BHATURE",
                "N\\A",
                "SALAD",
                "LASOONI CHUTNEY",
                "N\\A"
            ]
        }
    },
    "2026-07-19": {
        "day": "Sunday",
        "meals": {
            "Breakfast": [
                "ALOO PYAZ PARATHA",
                "DAHI, POHA",
                "CORNFLAKES",
                "BBJ (BUTTER/JAM)",
                "SEASONAL FRUIT",
                "BOILED EGG",
                "TEA/COFFEE/MILK"
            ],
            "Lunch": [
                "LOBIA CURRY",
                "ALOO GOBI",
                "PALAK DAL",
                "RICE",
                "PHULKA",
                "SALAD",
                "PICKLE",
                "JALJIRA",
                "N\\A"
            ],
            "Snacks": [
                "MUFFIN CAKE"
            ],
            "Dinner": [
                "CHICKAN KADHAI",
                "PANNER TIKKA MASALA",
                "DAL",
                "RICE",
                "PHULKA",
                "N\\A",
                "SALAD",
                "PICKLE",
                "GULABJAM"
            ]
        }
    }
}